sypht/__init__.py
sypht/__main__.py
sypht/client.py
sypht/util.py
sypht-0.5.19.dist-info/LICENSE
sypht-0.5.19.dist-info/METADATA
sypht-0.5.19.dist-info/WHEEL
sypht-0.5.19.dist-info/entry_points.txt
sypht-0.5.19.dist-info/top_level.txt
sypht-0.5.19.dist-info/RECORD
